{
  "applications": "*",
  "changelogDate": "20220516214140",
  "dto": "mapstruct",
  "embedded": false,
  "entityTableName": "restaurant",
  "fields": [
    {
      "fieldName": "nomRestaurant",
      "fieldType": "String"
    },
    {
      "fieldName": "adresseRestaurant",
      "fieldType": "String"
    },
    {
      "fieldName": "numRestaurant",
      "fieldType": "String"
    },
    {
      "fieldName": "dateOuverture",
      "fieldType": "Instant"
    },
    {
      "fieldName": "dateFermiture",
      "fieldType": "Instant"
    }
  ],
  "fluentMethods": true,
  "jpaMetamodelFiltering": false,
  "name": "Restaurant",
  "pagination": "pagination",
  "readOnly": false,
  "relationships": [
    {
      "otherEntityField": "nomResponsable",
      "otherEntityName": "ResponsableRestaurant",
      "otherEntityRelationshipName": "restaurant",
      "relationshipName": "ResponsableRestaurant",
      "relationshipType": "many-to-one"
    }
  ],
  "service": "serviceImpl"
}
